py2048/__init__.py
py2048/basefrontend.py
py2048/cell.py
py2048/core.py
py2048/grid.py
py2048/log.py
py2048/test.py
py2048/utils.py
py2048base-0.48.dist-info/METADATA
py2048base-0.48.dist-info/WHEEL
py2048base-0.48.dist-info/top_level.txt
py2048base-0.48.dist-info/zip-safe
py2048base-0.48.dist-info/RECORD
