Metadata-Version: 2.1
Name: py2048base
Version: 0.48
Summary: Python clone of the famous 2048 game.
Home-page: https://github.com/dasld/py2048base
Author: Daniel Diniz
Author-email: daniel_asl_diniz@protonmail.com
License: GPL
Platform: UNKNOWN
Classifier: Development Status :: 3 - Alpha
Classifier: Intended Audience :: Developers
Classifier: License :: OSI Approved :: GNU General Public License v3 or later (GPLv3+)
Classifier: Programming Language :: Python :: 3.9
Classifier: Topic :: Games/Entertainment :: Puzzle Games
Requires-Python: >=3.9
Requires-Dist: appdirs (>=1)
Requires-Dist: pytest (>=6)
